BlackScholesViewer.ipynb
LICENSE
MANIFEST.in
README.md
requirements.txt
setup.cfg
setup.py
ezvis3d/__init__.py
ezvis3d/__meta__.py
ezvis3d/_config.py
ezvis3d/_plot.py
ezvis3d/_state.py
ezvis3d/_vis3d.py
ezvis3d/_wrapper.py
ezvis3d/scripts.py
ezvis3d.egg-info/PKG-INFO
ezvis3d.egg-info/SOURCES.txt
ezvis3d.egg-info/dependency_links.txt
ezvis3d.egg-info/not-zip-safe
ezvis3d.egg-info/requires.txt
ezvis3d.egg-info/top_level.txt
ezvis3d/api/ezvis3d_dataset.json
ezvis3d/api/ezvis3d_dataset.tsv
ezvis3d/api/ezvis3d_method.json
ezvis3d/api/ezvis3d_method.tsv
ezvis3d/api/ezvis3d_option.json
ezvis3d/api/ezvis3d_option.tsv