Metadata-Version: 1.1
Name: ezvis3d
Version: 0.2.5
Summary: easy vis.js Graph3d js library wrapper, accessible from pandas dataframes in the IPython notebook
Home-page: https://github.com/oscar6echo/ezvis3d
Author: oscar6echo
Author-email: olivier.borderies@gmail.com
License: MIT
Download-URL: https://github.com/oscar6echo/ezvis3d/tarball/0.2.5
Keywords: vis.js,Graph3d,pandas,notebook,javascript
Platform: UNKNOWN
Classifier: Development Status :: 4 - Beta
Classifier: License :: OSI Approved :: MIT License
Classifier: Programming Language :: Python :: 2.7
Classifier: Programming Language :: Python :: 3.5
Classifier: Programming Language :: Python :: 3.6
